README.md
setup.py
exceptive/__init__.py
exceptive/decorators.py
exceptive/inheritance.py
exceptive.egg-info/PKG-INFO
exceptive.egg-info/SOURCES.txt
exceptive.egg-info/dependency_links.txt
exceptive.egg-info/not-zip-safe
exceptive.egg-info/top_level.txt