Metadata-Version: 2.1
Name: exceptive
Version: 0.1.8
Summary: Exceptive is a Python library that makes exception handling more programmatic and debuggable.
Home-page: https://github.com/erayerdin/exceptive
Author: Eray Erdin
Author-email: eraygezer.94@gmail.com
License: Apache License 2.0
Download-URL: https://github.com/erayerdin/exceptive/archive/master.zip
Platform: UNKNOWN
Classifier: Development Status :: 2 - Pre-Alpha
Classifier: Intended Audience :: Developers
Classifier: License :: OSI Approved :: Apache Software License
Classifier: Programming Language :: Python :: 3 :: Only
Classifier: Programming Language :: Python :: 3.4
Classifier: Programming Language :: Python :: 3.5
Classifier: Programming Language :: Python :: 3.6
Classifier: Topic :: Software Development
Classifier: Topic :: Software Development :: Testing
